wiki_tool_python/.mypy_cache/3.10/@plugins_snapshot.json
wiki_tool_python/.mypy_cache/3.10/_ast.data.json
wiki_tool_python/.mypy_cache/3.10/_ast.meta.json
wiki_tool_python/.mypy_cache/3.10/_collections_abc.data.json
wiki_tool_python/.mypy_cache/3.10/_collections_abc.meta.json
wiki_tool_python/.mypy_cache/3.10/_decimal.data.json
wiki_tool_python/.mypy_cache/3.10/_decimal.meta.json
wiki_tool_python/.mypy_cache/3.10/_operator.data.json
wiki_tool_python/.mypy_cache/3.10/_operator.meta.json
wiki_tool_python/.mypy_cache/3.10/_random.data.json
wiki_tool_python/.mypy_cache/3.10/_random.meta.json
wiki_tool_python/.mypy_cache/3.10/_stat.data.json
wiki_tool_python/.mypy_cache/3.10/_stat.meta.json
wiki_tool_python/.mypy_cache/3.10/_thread.data.json
wiki_tool_python/.mypy_cache/3.10/_thread.meta.json
wiki_tool_python/.mypy_cache/3.10/_typeshed/__init__.data.json
wiki_tool_python/.mypy_cache/3.10/_typeshed/__init__.meta.json
wiki_tool_python/.mypy_cache/3.10/_weakref.data.json
wiki_tool_python/.mypy_cache/3.10/_weakref.meta.json
wiki_tool_python/.mypy_cache/3.10/_weakrefset.data.json
wiki_tool_python/.mypy_cache/3.10/_weakrefset.meta.json
wiki_tool_python/.mypy_cache/3.10/abc.data.json
wiki_tool_python/.mypy_cache/3.10/abc.meta.json
wiki_tool_python/.mypy_cache/3.10/array.data.json
wiki_tool_python/.mypy_cache/3.10/array.meta.json
wiki_tool_python/.mypy_cache/3.10/builtins.data.json
wiki_tool_python/.mypy_cache/3.10/builtins.meta.json
wiki_tool_python/.mypy_cache/3.10/click/__init__.data.json
wiki_tool_python/.mypy_cache/3.10/click/__init__.meta.json
wiki_tool_python/.mypy_cache/3.10/click/_compat.data.json
wiki_tool_python/.mypy_cache/3.10/click/_compat.meta.json
wiki_tool_python/.mypy_cache/3.10/click/_termui_impl.data.json
wiki_tool_python/.mypy_cache/3.10/click/_termui_impl.meta.json
wiki_tool_python/.mypy_cache/3.10/click/_textwrap.data.json
wiki_tool_python/.mypy_cache/3.10/click/_textwrap.meta.json
wiki_tool_python/.mypy_cache/3.10/click/core.data.json
wiki_tool_python-0.3.0.dist-info/WHEEL
wiki_tool_python-0.3.0.dist-info/METADATA
wiki_tool_python-0.3.0.dist-info/RECORD
