Metadata-Version: 2.4
Name: wiki_tool_python
Version: 0.3.0
Summary: Script to perform tasks with websites on MediaWiki engine using API
Author: Artiom Khandamirov
Author-email: Artiom Khandamirov <t9max@yandex.ru>
License-Expression: MIT
Classifier: Development Status :: 4 - Beta
Classifier: Environment :: Console
Classifier: Operating System :: OS Independent
Requires-Dist: click>=8.1.7,<9
Requires-Dist: requests>=2.31.0,<3
Requires-Dist: requests-toolbelt>=1.0.0,<2
Requires-Python: >=3.12, <4
Project-URL: Repository, https://github.com/ArtUshak/wiki_tool_python/
